intentional_core/__about__.py
intentional_core/__init__.py
intentional_core/bot_interface.py
intentional_core/end_conversation.py
intentional_core/events.py
intentional_core/intent_routing.py
intentional_core/llm_client.py
intentional_core/tools.py
intentional_core/bot_structures/__init__.py
intentional_core/bot_structures/bot_structure.py
intentional_core/bot_structures/direct_to_llm.py
intentional_core/utils/__init__.py
intentional_core/utils/importing.py
intentional_core/utils/inheritance.py
intentional_core-0.0.1.dist-info/METADATA
intentional_core-0.0.1.dist-info/WHEEL
intentional_core-0.0.1.dist-info/licenses/LICENSE.txt
intentional_core-0.0.1.dist-info/RECORD
