Metadata-Version: 2.3
Name: intentional-core
Version: 0.0.1
Summary: Intentional is an open-source framework to build reliable, multimodal and multi-channel LLM chatbots that actually talk and behave as you expect.
Project-URL: Documentation, https://github.com/intentional-ai/intentional#readme
Project-URL: Issues, https://github.com/intentional-ai/intentional/issues
Project-URL: Source, https://github.com/intentional-ai/intentional
Author-email: ZanSara <github@zansara.dev>
License: AGPL-3.0-or-later
Classifier: Development Status :: 4 - Beta
Classifier: Programming Language :: Python
Classifier: Programming Language :: Python :: 3.9
Classifier: Programming Language :: Python :: 3.10
Classifier: Programming Language :: Python :: 3.11
Classifier: Programming Language :: Python :: 3.12
Classifier: Programming Language :: Python :: Implementation :: CPython
Classifier: Programming Language :: Python :: Implementation :: PyPy
Requires-Python: >=3.9
Requires-Dist: networkx
Requires-Dist: pyyaml
Requires-Dist: requests
Requires-Dist: structlog
